utilspy_g4/__init__.py
utilspy_g4-2.2.0.dist-info/LICENSE
utilspy_g4-2.2.0.dist-info/METADATA
utilspy_g4-2.2.0.dist-info/WHEEL
utilspy_g4-2.2.0.dist-info/top_level.txt
utilspy_g4-2.2.0.dist-info/RECORD
