Metadata-Version: 2.1
Name: utilspy-g4
Version: 2.2.0
Summary: Small utils for Python
Home-page: https://github.com/Genzo4/utilspy
Author: Genzo
Author-email: genzo@bk.ru
License: MIT
Project-URL: Bug Tracker, https://github.com/Genzo4/utilspy/issues
Keywords: utils,utilspy,g4,add ext,add_ext,del_ext,del ext,templated_remove_files,templated remove files,remove files,get_ext,get ext,int_to_2str,inttostr,int2str,get_files_count,files count,to_date,date,date_template,date template
Classifier: Development Status :: 5 - Production/Stable
Classifier: Programming Language :: Python :: 3
Classifier: Programming Language :: Python :: 3.6
Classifier: Programming Language :: Python :: 3.7
Classifier: Programming Language :: Python :: 3.8
Classifier: Programming Language :: Python :: 3.9
Classifier: Programming Language :: Python :: 3.10
Classifier: Programming Language :: Python :: 3.11
Classifier: License :: OSI Approved :: MIT License
Classifier: Operating System :: OS Independent
Classifier: Intended Audience :: Developers
Classifier: Natural Language :: English
Classifier: Natural Language :: Russian
Classifier: Topic :: Software Development
Classifier: Topic :: Software Development :: Libraries :: Python Modules
Classifier: Topic :: Utilities
Requires-Python: >=3.6
License-File: LICENSE
